{"version":3,"kind":"Article","sha256":"c7fc2e8d3027ad43327d366ecb751395d4d9d65fbbe560c2b52cf038880b60c8","slug":"contributing","location":"/docs/contributing.md","dependencies":[],"frontmatter":{"title":"Contributing","content_includes_title":false,"github":"https://github.com/WHO-Collaboratory/ebola-resources","source_url":"https://github.com/WHO-Collaboratory/ebola-resources/blob/main/docs/contributing.md","edit_url":"https://github.com/WHO-Collaboratory/ebola-resources/edit/main/docs/contributing.md","exports":[{"format":"md","filename":"contributing.md","url":"/ebola-resources/build/contributing-af0a571641296c7f24458ee538f06b98.md"}]},"mdast":{"type":"root","children":[{"type":"block","children":[{"type":"paragraph","position":{"start":{"line":3,"column":1},"end":{"line":3,"column":1}},"children":[{"type":"text","value":"This resource list is maintained by the Ebola Outbreak Analytics CoP. Contributions are welcome from anyone working on the 2026 DRC Ebola Bundibugyo response.","position":{"start":{"line":3,"column":1},"end":{"line":3,"column":1}},"key":"a2FPgQt1Si"}],"key":"mWTULnRlwl"},{"type":"block","children":[{"type":"list","children":[{"type":"listItem","children":[{"type":"link","url":"/formatting-guide","internal":true,"children":[{"type":"text","value":"Formatting guide","key":"Yu50YgCYGZ"}],"urlSource":"/formatting-guide","key":"nz3TDFpkiB"}],"key":"KNd3ubsaOY"},{"type":"listItem","children":[{"type":"link","url":"/maintainers","internal":true,"children":[{"type":"text","value":"Maintainers Guide","key":"dJHT0uXLK5"}],"urlSource":"/maintainers","key":"ZzbOC45Ded"}],"key":"S2aJAoLdZJ"}],"key":"rKLYxovqzg"}],"data":{"part":"toc:children"},"key":"fGvX9OMLNk"},{"type":"heading","depth":2,"position":{"start":{"line":9,"column":1},"end":{"line":9,"column":1}},"children":[{"type":"text","value":"Ways to contribute","position":{"start":{"line":9,"column":1},"end":{"line":9,"column":1}},"key":"PetOqqd30D"}],"identifier":"ways-to-contribute","label":"Ways to contribute","html_id":"ways-to-contribute","implicit":true,"key":"ZEgKnjNaTT"},{"type":"heading","depth":3,"position":{"start":{"line":11,"column":1},"end":{"line":11,"column":1}},"children":[{"type":"text","value":"1. Submit an issue (no coding needed)","position":{"start":{"line":11,"column":1},"end":{"line":11,"column":1}},"key":"eVPD905Bkl"}],"identifier":"id-1-submit-an-issue-no-coding-needed","label":"1. Submit an issue (no coding needed)","html_id":"id-1-submit-an-issue-no-coding-needed","implicit":true,"key":"WOxCDbGKlg"},{"type":"paragraph","position":{"start":{"line":13,"column":1},"end":{"line":13,"column":1}},"children":[{"type":"text","value":"Open a GitHub Issue using our structured form:","position":{"start":{"line":13,"column":1},"end":{"line":13,"column":1}},"key":"SqS9K8S3lo"}],"key":"PYTdzWx55h"},{"type":"paragraph","position":{"start":{"line":15,"column":1},"end":{"line":15,"column":1}},"children":[{"type":"link","url":"https://github.com/WHO-Collaboratory/ebola-resources/issues/new?template=new-resource.yml","position":{"start":{"line":15,"column":1},"end":{"line":15,"column":1}},"children":[{"type":"text","value":"Suggest a Resource","position":{"start":{"line":15,"column":1},"end":{"line":15,"column":1}},"key":"BXstSK6WBD"}],"urlSource":"https://github.com/WHO-Collaboratory/ebola-resources/issues/new?template=new-resource.yml","error":true,"key":"bs1scI6Hmq"}],"key":"szCVMfychd"},{"type":"paragraph","position":{"start":{"line":17,"column":1},"end":{"line":17,"column":1}},"children":[{"type":"text","value":"Fill in the fields — title, URL, type, section, authors, organisation, date, and a short description. A GitHub Action will create a draft page and open a Pull Request. A maintainer will review, adjust placement if needed, and merge.","position":{"start":{"line":17,"column":1},"end":{"line":17,"column":1}},"key":"WyVY3c8GXq"}],"key":"nAgiLEHc73"},{"type":"heading","depth":3,"position":{"start":{"line":19,"column":1},"end":{"line":19,"column":1}},"children":[{"type":"text","value":"2. Open a Pull Request directly","position":{"start":{"line":19,"column":1},"end":{"line":19,"column":1}},"key":"imOZeDgIcy"}],"identifier":"id-2-open-a-pull-request-directly","label":"2. Open a Pull Request directly","html_id":"id-2-open-a-pull-request-directly","implicit":true,"key":"WNc6Rc6pSh"},{"type":"paragraph","position":{"start":{"line":21,"column":1},"end":{"line":21,"column":1}},"children":[{"type":"text","value":"Create a ","position":{"start":{"line":21,"column":1},"end":{"line":21,"column":1}},"key":"zMvMNICK8D"},{"type":"inlineCode","value":".md","position":{"start":{"line":21,"column":1},"end":{"line":21,"column":1}},"key":"s88vMueQMX"},{"type":"text","value":" file in the appropriate section directory (e.g. ","position":{"start":{"line":21,"column":1},"end":{"line":21,"column":1}},"key":"HVhYuZxMRv"},{"type":"inlineCode","value":"docs/resources/dashboards/my-resource.md","position":{"start":{"line":21,"column":1},"end":{"line":21,"column":1}},"key":"eJmPWeH2lS"},{"type":"text","value":") and add an ","position":{"start":{"line":21,"column":1},"end":{"line":21,"column":1}},"key":"yxgKqxLY9e"},{"type":"inlineCode","value":"{include}","position":{"start":{"line":21,"column":1},"end":{"line":21,"column":1}},"key":"mymKBhCXxa"},{"type":"text","value":" directive to the section’s index file (e.g. ","position":{"start":{"line":21,"column":1},"end":{"line":21,"column":1}},"key":"d8uTMbGztU"},{"type":"inlineCode","value":"docs/resources/tools-index.md","position":{"start":{"line":21,"column":1},"end":{"line":21,"column":1}},"key":"ku9WuSvL6B"},{"type":"text","value":"). Use the format below.","position":{"start":{"line":21,"column":1},"end":{"line":21,"column":1}},"key":"UrGebvBceg"}],"key":"s1Pf9foZhe"},{"type":"heading","depth":2,"position":{"start":{"line":23,"column":1},"end":{"line":23,"column":1}},"children":[{"type":"text","value":"Resource page format","position":{"start":{"line":23,"column":1},"end":{"line":23,"column":1}},"key":"gPUr6ywRS3"}],"identifier":"resource-page-format","label":"Resource page format","html_id":"resource-page-format","implicit":true,"key":"JW3jbrkAnI"},{"type":"paragraph","position":{"start":{"line":25,"column":1},"end":{"line":25,"column":1}},"children":[{"type":"text","value":"Every resource page should include these mandatory metadata fields in a standardized header:","position":{"start":{"line":25,"column":1},"end":{"line":25,"column":1}},"key":"NXhR0VMCWS"}],"key":"H9LOgtIOGH"},{"type":"code","lang":"markdown","value":"# Resource Title\n\nType · **Organisation** · Authors · Date\n\nDescription of the resource — as much or as little as needed.\n\n[Visit resource](https://...)","position":{"start":{"line":27,"column":1},"end":{"line":35,"column":1}},"key":"PszJyZ97gH"},{"type":"table","position":{"start":{"line":37,"column":1},"end":{"line":45,"column":1}},"children":[{"type":"tableRow","position":{"start":{"line":37,"column":1},"end":{"line":37,"column":1}},"children":[{"type":"tableCell","header":true,"position":{"start":{"line":37,"column":1},"end":{"line":37,"column":1}},"children":[{"type":"text","value":"Field","position":{"start":{"line":37,"column":1},"end":{"line":37,"column":1}},"key":"AGtJRPyOuC"}],"key":"t19bjRVM99"},{"type":"tableCell","header":true,"position":{"start":{"line":37,"column":1},"end":{"line":37,"column":1}},"children":[{"type":"text","value":"Required","position":{"start":{"line":37,"column":1},"end":{"line":37,"column":1}},"key":"cySoitld0v"}],"key":"u4obzwrbNC"},{"type":"tableCell","header":true,"position":{"start":{"line":37,"column":1},"end":{"line":37,"column":1}},"children":[{"type":"text","value":"Example","position":{"start":{"line":37,"column":1},"end":{"line":37,"column":1}},"key":"fDV2ZY9AMd"}],"key":"RltOBW7fGD"}],"key":"t1m2Ka2FJs"},{"type":"tableRow","position":{"start":{"line":39,"column":1},"end":{"line":39,"column":1}},"children":[{"type":"tableCell","position":{"start":{"line":39,"column":1},"end":{"line":39,"column":1}},"children":[{"type":"text","value":"Title","position":{"start":{"line":39,"column":1},"end":{"line":39,"column":1}},"key":"OoNAaPfPgs"}],"key":"hSt1pK9wzA"},{"type":"tableCell","position":{"start":{"line":39,"column":1},"end":{"line":39,"column":1}},"children":[{"type":"text","value":"Yes","position":{"start":{"line":39,"column":1},"end":{"line":39,"column":1}},"key":"Q3J6skS4kr"}],"key":"DavZJCHTbT"},{"type":"tableCell","position":{"start":{"line":39,"column":1},"end":{"line":39,"column":1}},"children":[{"type":"inlineCode","value":"# INRB UMIE Dashboard","position":{"start":{"line":39,"column":1},"end":{"line":39,"column":1}},"key":"fXryraun9K"}],"key":"umMLop2g1v"}],"key":"vHpI4D1oZK"},{"type":"tableRow","position":{"start":{"line":40,"column":1},"end":{"line":40,"column":1}},"children":[{"type":"tableCell","position":{"start":{"line":40,"column":1},"end":{"line":40,"column":1}},"children":[{"type":"text","value":"Type","position":{"start":{"line":40,"column":1},"end":{"line":40,"column":1}},"key":"vzF6WZ3Mgi"}],"key":"tydFSmNScu"},{"type":"tableCell","position":{"start":{"line":40,"column":1},"end":{"line":40,"column":1}},"children":[{"type":"text","value":"Yes","position":{"start":{"line":40,"column":1},"end":{"line":40,"column":1}},"key":"Ac05T3XjhA"}],"key":"hrwYQSQIkJ"},{"type":"tableCell","position":{"start":{"line":40,"column":1},"end":{"line":40,"column":1}},"children":[{"type":"text","value":"Dashboard, Report, Tool, Dataset, Package","position":{"start":{"line":40,"column":1},"end":{"line":40,"column":1}},"key":"gM6pRG63KL"}],"key":"e2lXQsheim"}],"key":"eGNqXjwFME"},{"type":"tableRow","position":{"start":{"line":41,"column":1},"end":{"line":41,"column":1}},"children":[{"type":"tableCell","position":{"start":{"line":41,"column":1},"end":{"line":41,"column":1}},"children":[{"type":"text","value":"Organisation","position":{"start":{"line":41,"column":1},"end":{"line":41,"column":1}},"key":"lRs4MUQiuJ"}],"key":"DoT2hs2N5A"},{"type":"tableCell","position":{"start":{"line":41,"column":1},"end":{"line":41,"column":1}},"children":[{"type":"text","value":"Yes","position":{"start":{"line":41,"column":1},"end":{"line":41,"column":1}},"key":"Ed2uyErtXq"}],"key":"yFH1X6h480"},{"type":"tableCell","position":{"start":{"line":41,"column":1},"end":{"line":41,"column":1}},"children":[{"type":"text","value":"Imperial College London","position":{"start":{"line":41,"column":1},"end":{"line":41,"column":1}},"key":"akIauIvC0f"}],"key":"W0VPY5UucV"}],"key":"sCy9tj4rLv"},{"type":"tableRow","position":{"start":{"line":42,"column":1},"end":{"line":42,"column":1}},"children":[{"type":"tableCell","position":{"start":{"line":42,"column":1},"end":{"line":42,"column":1}},"children":[{"type":"text","value":"Authors","position":{"start":{"line":42,"column":1},"end":{"line":42,"column":1}},"key":"BE0221xqYh"}],"key":"uqtzq523Za"},{"type":"tableCell","position":{"start":{"line":42,"column":1},"end":{"line":42,"column":1}},"children":[{"type":"text","value":"Yes","position":{"start":{"line":42,"column":1},"end":{"line":42,"column":1}},"key":"Br3ezhmOL4"}],"key":"Z0nVuKdJRg"},{"type":"tableCell","position":{"start":{"line":42,"column":1},"end":{"line":42,"column":1}},"children":[{"type":"text","value":"Ruth McCabe et al.","position":{"start":{"line":42,"column":1},"end":{"line":42,"column":1}},"key":"uyN9Sbcu7P"}],"key":"F00EBpAwsC"}],"key":"KjnfeMz8ji"},{"type":"tableRow","position":{"start":{"line":43,"column":1},"end":{"line":43,"column":1}},"children":[{"type":"tableCell","position":{"start":{"line":43,"column":1},"end":{"line":43,"column":1}},"children":[{"type":"text","value":"Date","position":{"start":{"line":43,"column":1},"end":{"line":43,"column":1}},"key":"Rbb39okH4d"}],"key":"fcOeIMBJYr"},{"type":"tableCell","position":{"start":{"line":43,"column":1},"end":{"line":43,"column":1}},"children":[{"type":"text","value":"Yes","position":{"start":{"line":43,"column":1},"end":{"line":43,"column":1}},"key":"x8DT3nGfZP"}],"key":"NnexB66vt0"},{"type":"tableCell","position":{"start":{"line":43,"column":1},"end":{"line":43,"column":1}},"children":[{"type":"text","value":"2026-05-20","position":{"start":{"line":43,"column":1},"end":{"line":43,"column":1}},"key":"Jcun4sQDMP"}],"key":"jN9IlXDarr"}],"key":"VDCWVMf6YV"},{"type":"tableRow","position":{"start":{"line":44,"column":1},"end":{"line":44,"column":1}},"children":[{"type":"tableCell","position":{"start":{"line":44,"column":1},"end":{"line":44,"column":1}},"children":[{"type":"text","value":"Link","position":{"start":{"line":44,"column":1},"end":{"line":44,"column":1}},"key":"msbczknAPk"}],"key":"jXdWDRTlVL"},{"type":"tableCell","position":{"start":{"line":44,"column":1},"end":{"line":44,"column":1}},"children":[{"type":"text","value":"Yes","position":{"start":{"line":44,"column":1},"end":{"line":44,"column":1}},"key":"jR6422IpRx"}],"key":"uwH94HMPSH"},{"type":"tableCell","position":{"start":{"line":44,"column":1},"end":{"line":44,"column":1}},"children":[{"type":"inlineCode","value":"[Visit resource](https://...)","position":{"start":{"line":44,"column":1},"end":{"line":44,"column":1}},"key":"b9kHB4K629"}],"key":"fTlh1e8Le3"}],"key":"EdbL0A7lTw"},{"type":"tableRow","position":{"start":{"line":45,"column":1},"end":{"line":45,"column":1}},"children":[{"type":"tableCell","position":{"start":{"line":45,"column":1},"end":{"line":45,"column":1}},"children":[{"type":"text","value":"Description","position":{"start":{"line":45,"column":1},"end":{"line":45,"column":1}},"key":"F7Vs5IWgE3"}],"key":"VxBui184a7"},{"type":"tableCell","position":{"start":{"line":45,"column":1},"end":{"line":45,"column":1}},"children":[{"type":"text","value":"Yes","position":{"start":{"line":45,"column":1},"end":{"line":45,"column":1}},"key":"z3zbztkeME"}],"key":"WmIk6M7IVO"},{"type":"tableCell","position":{"start":{"line":45,"column":1},"end":{"line":45,"column":1}},"children":[{"type":"text","value":"Free-text Markdown","position":{"start":{"line":45,"column":1},"end":{"line":45,"column":1}},"key":"z0czPE6ie4"}],"key":"hXfD0tCIE5"}],"key":"yd38ZSEIJu"}],"key":"vjKkeDH0lE"},{"type":"paragraph","position":{"start":{"line":47,"column":1},"end":{"line":47,"column":1}},"children":[{"type":"text","value":"Beyond the header, the page body is free-text Markdown. See the ","position":{"start":{"line":47,"column":1},"end":{"line":47,"column":1}},"key":"K6lWwAdLoY"},{"type":"link","url":"/formatting-guide","position":{"start":{"line":47,"column":1},"end":{"line":47,"column":1}},"children":[{"type":"text","value":"Formatting guide","position":{"start":{"line":47,"column":1},"end":{"line":47,"column":1}},"key":"R9J6SUWiQJ"}],"urlSource":"formatting-guide.md","dataUrl":"/formatting-guide.json","internal":true,"protocol":"file","key":"rHAFGRtdkl"},{"type":"text","value":" for examples of tables, code blocks, admonitions, math, and more.","position":{"start":{"line":47,"column":1},"end":{"line":47,"column":1}},"key":"tZjzYQ2R8l"}],"key":"aDICAipKZu"},{"type":"heading","depth":2,"position":{"start":{"line":49,"column":1},"end":{"line":49,"column":1}},"children":[{"type":"text","value":"What belongs here","position":{"start":{"line":49,"column":1},"end":{"line":49,"column":1}},"key":"xdwqn911a5"}],"identifier":"what-belongs-here","label":"What belongs here","html_id":"what-belongs-here","implicit":true,"key":"IYRNRANtlt"},{"type":"paragraph","position":{"start":{"line":51,"column":1},"end":{"line":51,"column":1}},"children":[{"type":"text","value":"We curate resources that are:","position":{"start":{"line":51,"column":1},"end":{"line":51,"column":1}},"key":"eDeI4VjcKw"}],"key":"KgQ6qQz6OE"},{"type":"list","ordered":false,"spread":false,"position":{"start":{"line":53,"column":1},"end":{"line":56,"column":1}},"children":[{"type":"listItem","spread":true,"position":{"start":{"line":53,"column":1},"end":{"line":53,"column":1}},"children":[{"type":"paragraph","children":[{"type":"strong","position":{"start":{"line":53,"column":1},"end":{"line":53,"column":1}},"children":[{"type":"text","value":"Relevant","position":{"start":{"line":53,"column":1},"end":{"line":53,"column":1}},"key":"t8O4vmcYHL"}],"key":"Kmsg8Hd89C"},{"type":"text","value":" to the 2026 DRC Ebola Bundibugyo outbreak response","position":{"start":{"line":53,"column":1},"end":{"line":53,"column":1}},"key":"exX83uogsq"}],"key":"NEubsbBrJk"}],"key":"OKiy5qcHLc"},{"type":"listItem","spread":true,"position":{"start":{"line":54,"column":1},"end":{"line":54,"column":1}},"children":[{"type":"paragraph","children":[{"type":"strong","position":{"start":{"line":54,"column":1},"end":{"line":54,"column":1}},"children":[{"type":"text","value":"Publicly accessible","position":{"start":{"line":54,"column":1},"end":{"line":54,"column":1}},"key":"M24pMp8N3Q"}],"key":"KBr3JTJcC0"},{"type":"text","value":" (or with a clear access path)","position":{"start":{"line":54,"column":1},"end":{"line":54,"column":1}},"key":"YMTky0MElA"}],"key":"abr094RMxX"}],"key":"OSb5Y8eOLX"},{"type":"listItem","spread":true,"position":{"start":{"line":55,"column":1},"end":{"line":56,"column":1}},"children":[{"type":"paragraph","children":[{"type":"strong","position":{"start":{"line":55,"column":1},"end":{"line":55,"column":1}},"children":[{"type":"text","value":"Actionable","position":{"start":{"line":55,"column":1},"end":{"line":55,"column":1}},"key":"Rq0NVKdsSV"}],"key":"lbzaScN1NC"},{"type":"text","value":" — dashboards, datasets, tools, reports, and packages that responders and researchers can use","position":{"start":{"line":55,"column":1},"end":{"line":55,"column":1}},"key":"E1gzF0W7eH"}],"key":"yia52aptwy"}],"key":"Sli6HnxEko"}],"key":"wN8pgi6XtQ"},{"type":"paragraph","position":{"start":{"line":57,"column":1},"end":{"line":57,"column":1}},"children":[{"type":"text","value":"If a resource doesn’t fit an existing section, mention that in your issue or PR — we can create new sections as the response evolves.","position":{"start":{"line":57,"column":1},"end":{"line":57,"column":1}},"key":"jLsj0xCur5"}],"key":"PHyqroizJP"}],"key":"rbCkBCuQPt"}],"key":"TWGZMTPZmz"},"references":{"cite":{"order":[],"data":{}}},"footer":{"navigation":{"prev":{"title":"Community meeting materials","short_title":"Community Meetings","url":"/community-meetings","group":"Ebola Outbreak Analytics - CoP Resources"},"next":{"title":"Formatting guide","url":"/formatting-guide","group":"Ebola Outbreak Analytics - CoP Resources"}}},"domain":"http://localhost:3000"}