{"version":3,"kind":"Article","sha256":"d6d1ab9b7cc159e4b3d6252e54506bfff15a7e0ed4074cdffa60fcf3fb016751","slug":"emerging-evidence","location":"/docs/resources/emerging-evidence.md","dependencies":[],"frontmatter":{"title":"Emerging evidence","content_includes_title":false,"github":"https://github.com/WHO-Collaboratory/ebola-resources","source_url":"https://github.com/WHO-Collaboratory/ebola-resources/blob/main/docs/resources/emerging-evidence.md","edit_url":"https://github.com/WHO-Collaboratory/ebola-resources/edit/main/docs/resources/emerging-evidence.md","exports":[{"format":"md","filename":"emerging-evidence.md","url":"/ebola-resources/build/emerging-evidence-a2f2324a43636a4ca1c2df98058319c3.md"}]},"mdast":{"type":"root","children":[{"type":"block","children":[{"type":"paragraph","position":{"start":{"line":3,"column":1},"end":{"line":3,"column":1}},"children":[{"type":"text","value":"Recent analyses and preprints related to the 2026 DRC Ebola Bundibugyo outbreak. This section collects modelling outputs, risk assessments, and clinical evidence as they become available during the response.","position":{"start":{"line":3,"column":1},"end":{"line":3,"column":1}},"key":"rIcTpOdhIX"}],"key":"xroVbxPDjG"},{"type":"heading","depth":2,"position":{"start":{"line":5,"column":1},"end":{"line":5,"column":1}},"children":[{"type":"text","value":"Sub-sections","position":{"start":{"line":5,"column":1},"end":{"line":5,"column":1}},"key":"sVPxZBGQvc"}],"identifier":"sub-sections","label":"Sub-sections","html_id":"sub-sections","implicit":true,"key":"wWJS6JTcB7"},{"type":"list","ordered":false,"spread":false,"position":{"start":{"line":7,"column":1},"end":{"line":9,"column":1}},"children":[{"type":"listItem","spread":true,"position":{"start":{"line":7,"column":1},"end":{"line":9,"column":1}},"children":[{"type":"paragraph","children":[{"type":"link","url":"/outbreak-size","position":{"start":{"line":7,"column":1},"end":{"line":7,"column":1}},"children":[{"type":"text","value":"Outbreak size estimates","position":{"start":{"line":7,"column":1},"end":{"line":7,"column":1}},"key":"tgMQsPfvaG"}],"urlSource":"outbreak-size.md","dataUrl":"/outbreak-size.json","internal":true,"protocol":"file","key":"Y5s56IOlWY"},{"type":"text","value":" — Estimates of current and projected outbreak size\nRecent analyses and assessments related to the 2026 DRC Ebola Bundibugyo outbreak.","position":{"start":{"line":7,"column":1},"end":{"line":7,"column":1}},"key":"lr1CAsgamq"}],"key":"tePbgI7EOf"}],"key":"JwggWreXTa"}],"key":"dR5zHHMk4n"},{"type":"block","children":[{"type":"list","children":[{"type":"listItem","children":[{"type":"link","url":"/literature","internal":true,"children":[{"type":"text","value":"Literature","key":"VTnYd8LI4y"}],"urlSource":"/literature","key":"RZYpM4612S"}],"key":"GJkIIpWolx"},{"type":"listItem","children":[{"type":"link","url":"/outbreak-size","internal":true,"children":[{"type":"text","value":"Outbreak Size","key":"drwCVvegbJ"}],"urlSource":"/outbreak-size","key":"dZwNoIVNWW"}],"key":"LdbgWpkLux"},{"type":"listItem","children":[{"type":"link","url":"/risk-of-spread","internal":true,"children":[{"type":"text","value":"Risk of Spread","key":"hiY1Xs6Se1"}],"urlSource":"/risk-of-spread","key":"v91BNb7od5"}],"key":"wpbHihPEFx"},{"type":"listItem","children":[{"type":"link","url":"/therapeutics-vaccines","internal":true,"children":[{"type":"text","value":"Therapeutics & Vaccines","key":"qXThkXn9F8"}],"urlSource":"/therapeutics-vaccines","key":"jVCnaAGi1x"}],"key":"EMUaAi92ss"}],"key":"qVW9RnPfjY"}],"data":{"part":"toc:children"},"key":"yByOfS12oD"}],"key":"EmqStZdv2Q"}],"key":"klsTCfBoTO"},"references":{"cite":{"order":[],"data":{}}},"footer":{"navigation":{"prev":{"title":"Humanitarian","url":"/humanitarian","group":"Ebola Outbreak Analytics - CoP Resources"},"next":{"title":"Literature","url":"/literature","group":"Ebola Outbreak Analytics - CoP Resources"}}},"domain":"http://localhost:3000"}