{"version":3,"kind":"Article","sha256":"d6d1ab9b7cc159e4b3d6252e54506bfff15a7e0ed4074cdffa60fcf3fb016751","slug":"emerging-evidence","location":"/docs/resources/emerging-evidence.md","dependencies":[],"frontmatter":{"title":"Emerging evidence","content_includes_title":false,"github":"https://github.com/WHO-Collaboratory/ebola-resources","source_url":"https://github.com/WHO-Collaboratory/ebola-resources/blob/main/docs/resources/emerging-evidence.md","edit_url":"https://github.com/WHO-Collaboratory/ebola-resources/edit/main/docs/resources/emerging-evidence.md","exports":[{"format":"md","filename":"emerging-evidence.md","url":"/ebola-resources/build/emerging-evidence-741f534521c4497a19b918476d8702e9.md"}]},"mdast":{"type":"root","children":[{"type":"block","children":[{"type":"paragraph","position":{"start":{"line":3,"column":1},"end":{"line":3,"column":1}},"children":[{"type":"text","value":"Recent analyses and preprints related to the 2026 DRC Ebola Bundibugyo outbreak. This section collects modelling outputs, risk assessments, and clinical evidence as they become available during the response.","position":{"start":{"line":3,"column":1},"end":{"line":3,"column":1}},"key":"YY1FPVMtSS"}],"key":"CMA3gctPg7"},{"type":"heading","depth":2,"position":{"start":{"line":5,"column":1},"end":{"line":5,"column":1}},"children":[{"type":"text","value":"Sub-sections","position":{"start":{"line":5,"column":1},"end":{"line":5,"column":1}},"key":"EF5PAaOpN9"}],"identifier":"sub-sections","label":"Sub-sections","html_id":"sub-sections","implicit":true,"key":"aLVoWXdjjq"},{"type":"list","ordered":false,"spread":false,"position":{"start":{"line":7,"column":1},"end":{"line":9,"column":1}},"children":[{"type":"listItem","spread":true,"position":{"start":{"line":7,"column":1},"end":{"line":9,"column":1}},"children":[{"type":"paragraph","children":[{"type":"link","url":"/outbreak-size","position":{"start":{"line":7,"column":1},"end":{"line":7,"column":1}},"children":[{"type":"text","value":"Outbreak size estimates","position":{"start":{"line":7,"column":1},"end":{"line":7,"column":1}},"key":"lz2mwVwpco"}],"urlSource":"outbreak-size.md","dataUrl":"/outbreak-size.json","internal":true,"protocol":"file","key":"KIZDXpYFu6"},{"type":"text","value":" — Estimates of current and projected outbreak size\nRecent analyses and assessments related to the 2026 DRC Ebola Bundibugyo outbreak.","position":{"start":{"line":7,"column":1},"end":{"line":7,"column":1}},"key":"NZo5PBkqmi"}],"key":"WV1FceYmEg"}],"key":"RWbhE99S2H"}],"key":"Kwpum7FZL0"},{"type":"block","children":[{"type":"list","children":[{"type":"listItem","children":[{"type":"link","url":"/literature","internal":true,"children":[{"type":"text","value":"Literature","key":"Nstx9WYQIc"}],"urlSource":"/literature","key":"mPoUZohBBT"}],"key":"h6VVfcRt1h"},{"type":"listItem","children":[{"type":"link","url":"/outbreak-size","internal":true,"children":[{"type":"text","value":"Outbreak Size","key":"cCBets1fos"}],"urlSource":"/outbreak-size","key":"B3tgL9xJot"}],"key":"zigKCSkP0u"},{"type":"listItem","children":[{"type":"link","url":"/risk-of-spread","internal":true,"children":[{"type":"text","value":"Risk of Spread","key":"ekTHpG5Pc6"}],"urlSource":"/risk-of-spread","key":"QWoRJ8hzDu"}],"key":"HWKKXvqtQj"},{"type":"listItem","children":[{"type":"link","url":"/therapeutics-vaccines","internal":true,"children":[{"type":"text","value":"Therapeutics & Vaccines","key":"hVjFPCR9kZ"}],"urlSource":"/therapeutics-vaccines","key":"w794sMTJgu"}],"key":"E28Xpjvr2C"}],"key":"ZdbdWhlCkP"}],"data":{"part":"toc:children"},"key":"xyWc2sIC7a"}],"key":"AhMIwRspqE"}],"key":"GmQGJUzVGJ"},"references":{"cite":{"order":[],"data":{}}},"footer":{"navigation":{"prev":{"title":"Humanitarian","url":"/humanitarian","group":"Ebola Outbreak Analytics - CoP Resources"},"next":{"title":"Literature","url":"/literature","group":"Ebola Outbreak Analytics - CoP Resources"}}},"domain":"http://localhost:3000"}